lvmcryo/__init__.py
lvmcryo/__main__.py
lvmcryo/config.py
lvmcryo/config.yaml
lvmcryo/handlers/__init__.py
lvmcryo/handlers/ln2.py
lvmcryo/handlers/thermistor.py
lvmcryo/handlers/valve.py
lvmcryo/notifier.py
lvmcryo/runner.py
lvmcryo/scripts/manual-fill.sh
lvmcryo/server/__init__.py
lvmcryo/server/app.py
lvmcryo/templates/alert_message.html
lvmcryo/templates/success_message.html
lvmcryo/tools.py
lvmcryo/validate.py
lvmcryo-0.5.1.dist-info/WHEEL
lvmcryo-0.5.1.dist-info/entry_points.txt
lvmcryo-0.5.1.dist-info/METADATA
lvmcryo-0.5.1.dist-info/RECORD
